koho/__init__.py
koho/_version.py
koho/sklearn/__init__.py
koho/sklearn/_decision_forest.py
koho/sklearn/_decision_tree.py
koho/sklearn/_decision_tree_python.py
koho-0.0.1.dist-info/LICENSE
koho-0.0.1.dist-info/METADATA
koho-0.0.1.dist-info/WHEEL
koho-0.0.1.dist-info/top_level.txt
koho-0.0.1.dist-info/RECORD
