Metadata-Version: 2.1
Name: koho
Version: 0.0.1
Summary: Decision Forest C++ library with a scikit-learn compatible Python interface
Home-page: https://koho.readthedocs.io/en/latest/
Author: AI Werkstatt(TM) www.aiwerkstatt.com
Author-email: drh@aiwerkstatt.com
Maintainer: AI Werkstatt(TM) www.aiwerkstatt.com
Maintainer-email: drh@aiwerkstatt.com
License: New BSD License
Download-URL: https://github.com/aiwerkstatt/koho
Platform: UNKNOWN
Classifier: Topic :: Scientific/Engineering :: Artificial Intelligence
Classifier: Intended Audience :: Science/Research
Classifier: Natural Language :: English
Classifier: License :: OSI Approved :: BSD License
Classifier: Development Status :: 1 - Planning
Classifier: Programming Language :: Python :: 3.5
Classifier: Programming Language :: Python :: 3.6
Classifier: Programming Language :: Python :: 3.7
Classifier: Operating System :: Microsoft :: Windows
Classifier: Operating System :: POSIX
Classifier: Operating System :: Unix
Classifier: Operating System :: MacOS
Requires-Dist: numpy
Requires-Dist: scipy
Requires-Dist: scikit-learn
Provides-Extra: docs
Requires-Dist: sphinx ; extra == 'docs'
Requires-Dist: sphinx-gallery ; extra == 'docs'
Requires-Dist: sphinx-rtd-theme ; extra == 'docs'
Requires-Dist: numpydoc ; extra == 'docs'
Requires-Dist: matplotlib ; extra == 'docs'
Provides-Extra: tests
Requires-Dist: pytest ; extra == 'tests'
Requires-Dist: pytest-cov ; extra == 'tests'
